{
  "restaurant_availability": {
    "restaurant_id": "1124747",
    "delivery_fee": {
      "amount": 99,
      "currency": "USD"
    },
    "delivery_fee_without_discounts": {
      "amount": 99,
      "currency": "USD"
    },
    "delivery_fee_estimate": {
      "amount": 99,
      "currency": "USD"
    },
    "delivery_fee_as_percentage": 0,
    "delivery_fee_taxable": true,
    "delivery_fee_allocation_info": {
      "attribution": "GRUBHUB"
    },
    "order_minimum": {
      "amount": 0,
      "currency": "USD"
    },
    "sales_tax": 8.7,
    "delivery_offered_to_diner_location": false,
    "open": true,
    "open_delivery": true,
    "open_pickup": true,
    "available_for_delivery": true,
    "available_for_pickup": true,
    "delivery_estimate": 60,
    "delivery_estimate_range": "{\"maximum\":70,\"minimum\":60}",
    "delivery_estimate_range_v2": {
      "maximum": 70,
      "minimum": 60
    },
    "pickup_estimate": 20,
    "pickup_estimate_range": "{\"maximum\":30,\"minimum\":20}",
    "pickup_estimate_range_v2": {
      "maximum": 30,
      "minimum": 20
    },
    "cash_accepted": false,
    "credit_card_accepted": true,
    "paypal_accepted": false,
    "time_zone_id": "America/Phoenix",
    "time_zone_offset": -25200000,
    "tracker": true,
    "delivery_cutoff": 15,
    "pickup_cutoff": 30,
    "available_hours": [
      {
        "day_of_week": 1,
        "time_ranges": [
          "17:30-06:59"
        ]
      },
      {
        "day_of_week": 2,
        "time_ranges": [
          "17:30-06:59"
        ]
      },
      {
        "day_of_week": 3,
        "time_ranges": [
          "17:30-06:59"
        ]
      },
      {
        "day_of_week": 4,
        "time_ranges": [
          "17:30-06:59"
        ]
      },
      {
        "day_of_week": 5,
        "time_ranges": [
          "17:30-06:59"
        ]
      },
      {
        "day_of_week": 6,
        "time_ranges": [
          "17:30-06:59"
        ]
      },
      {
        "day_of_week": 7,
        "time_ranges": [
          "17:30-06:59"
        ]
      }
    ],
    "available_hours_pickup": [
      {
        "day_of_week": 1,
        "time_ranges": [
          "18:00-07:00"
        ]
      },
      {
        "day_of_week": 2,
        "time_ranges": [
          "18:00-07:00"
        ]
      },
      {
        "day_of_week": 3,
        "time_ranges": [
          "18:00-07:00"
        ]
      },
      {
        "day_of_week": 4,
        "time_ranges": [
          "18:00-07:00"
        ]
      },
      {
        "day_of_week": 5,
        "time_ranges": [
          "18:00-07:00"
        ]
      },
      {
        "day_of_week": 6,
        "time_ranges": [
          "18:00-07:00"
        ]
      },
      {
        "day_of_week": 7,
        "time_ranges": [
          "18:00-07:00"
        ]
      }
    ],
    "future_order_available_hours_delivery": [
      {
        "day_of_week": 1,
        "time_ranges": [
          "18:30-07:59"
        ]
      },
      {
        "day_of_week": 2,
        "time_ranges": [
          "18:30-07:59"
        ]
      },
      {
        "day_of_week": 3,
        "time_ranges": [
          "18:30-07:59"
        ]
      },
      {
        "day_of_week": 4,
        "time_ranges": [
          "18:30-07:59"
        ]
      },
      {
        "day_of_week": 5,
        "time_ranges": [
          "18:30-07:59"
        ]
      },
      {
        "day_of_week": 6,
        "time_ranges": [
          "18:30-07:59"
        ]
      },
      {
        "day_of_week": 7,
        "time_ranges": [
          "18:30-07:59"
        ]
      }
    ],
    "future_order_available_hours_pickup": [
      {
        "day_of_week": 1,
        "time_ranges": [
          "18:20-07:20"
        ]
      },
      {
        "day_of_week": 2,
        "time_ranges": [
          "18:20-07:20"
        ]
      },
      {
        "day_of_week": 3,
        "time_ranges": [
          "18:20-07:20"
        ]
      },
      {
        "day_of_week": 4,
        "time_ranges": [
          "18:20-07:20"
        ]
      },
      {
        "day_of_week": 5,
        "time_ranges": [
          "18:20-07:20"
        ]
      },
      {
        "day_of_week": 6,
        "time_ranges": [
          "18:20-07:20"
        ]
      },
      {
        "day_of_week": 7,
        "time_ranges": [
          "18:20-07:20"
        ]
      }
    ],
    "min_delivery_fee": {
      "amount": 199,
      "currency": "USD"
    },
    "catering_info": {
      "catering_sibling_id": null,
      "order_thresholds": {
        "currency": "USD",
        "order_price_bucket_list": [
          {
            "amount": 250,
            "buffer_minutes": 30
          }
        ]
      },
      "catering": false
    },
    "next_open_closed_info": {
      "next_order_send_time_delivery": "2021-02-06T22:47:08.693Z",
      "next_order_send_time_pickup": "2021-02-06T22:47:08.693Z",
      "next_delivery_time": "2021-02-06T23:47:08.693Z",
      "next_pickup_time": "2021-02-06T23:07:08.693Z",
      "next_cutoff_order_send_time_delivery": "2021-02-07T06:44:00.000Z",
      "next_cutoff_order_send_time_pickup": "2021-02-07T06:30:00.000Z",
      "order_tiers": [
        {
          "threshold_type": "ORDER_AMOUNT_CENTS",
          "threshold": 15000,
          "additional_prep_time_minutes": 20,
          "next_delivery_time": "2021-02-07T00:07:08.693Z",
          "next_order_send_time_delivery": "2021-02-06T22:47:08.693Z",
          "next_pickup_time": "2021-02-06T23:27:08.693Z",
          "next_order_send_time_pickup": "2021-02-06T22:47:08.693Z"
        }
      ]
    },
    "allowable_order_types": [
      "standard"
    ],
    "service_fee": {
      "name": "Service fee",
      "description": "A service fee of 1.0% for delivery orders will be charged with Southwest Grillers.",
      "delivery_fee": {
        "fee_type": "PERCENT",
        "percent_value": 1
      },
      "delivery_service_fee_allocation_info": {
        "attribution": "GRUBHUB"
      },
      "fee_allocation_info": {
        "fee_allocation_type": "GRUBHUB"
      }
    },
    "small_order_fee": {
      "name": "Small order delivery fee",
      "description": "A small order delivery fee applies to your Southwest Grillers subtotal of $9.89 or less.",
      "minimum_order_value_cents": 1000,
      "fee": {
        "fee_type": "FLAT",
        "flat_cents_value": {
          "amount": 200,
          "currency": "USD"
        }
      },
      "fee_allocation_info": {
        "attribution": "GRUBHUB"
      }
    },
    "fee_display_setting": {
      "search_display_setting": null,
      "menu_display_setting": {
        "id": "UniversalControl",
        "subtitle_fee_styled_text": {
          "text": "",
          "text_style": "DEFAULT"
        },
        "disclaimer": null
      }
    },
    "grouped_overrides_availability": {
      "delivery_blacked_out": false,
      "pickup_blacked_out": false,
      "delivery_soft_blacked_out": false,
      "pickup_soft_blacked_out": false,
      "delivery_estimate_in_minutes": null,
      "inundated": false
    },
    "contact_free_required": false,
    "cutoff_for_delivery": false,
    "cutoff_for_pickup": false,
    "blacked_out": false,
    "white_in": false,
    "inundated": false
  },
  "restaurant": {
    "id": "1124747",
    "restaurant_hash": "f15122cb42a89fa17a7e49a714cba451",
    "merchant_uuid": "K0xr8D9rEembfcN-L6MKbQ",
    "package_state_type_id": 2,
    "duplicate": false,
    "name": "Southwest Grillers",
    "address": {
      "locality": "Tucson",
      "region": "AZ",
      "postal_code": "85719-5049",
      "zip": "85719",
      "street_address": "940 E University Blvd",
      "country": "USA",
      "time_zone_id": "America/Phoenix"
    },
    "cross_street_required": false,
    "premium": true,
    "online_ordering_available": true,
    "pickup_offered": true,
    "phone_ordering_available": true,
    "phone_number_for_delivery": "5209553978",
    "suppress_diner_phone_contact": false,
    "latitude": "32.23131942",
    "longitude": "-110.95738984",
    "city_id": 22,
    "managed_delivery": true,
    "minimum_tip_percent": 10.0,
    "default_tip_percent": 20.0,
    "minimum_tip": {
      "amount": 200,
      "currency": "USD"
    },
    "logo": "https://media-cdn.grubhub.com/image/upload/v1551889393/pzkxn5p5uqllcgtydipf.jpg",
    "group_ids": [],
    "has_coupons": false,
    "is_new": false,
    "routing_number": "2132128693",
    "cuisines": [
      "American"
    ],
    "menu_category_list": [
      {
        "id": -975606837,
        "menu_category_id": "3319360459",
        "name": "Starters",
        "menu_item_list": [
          {
            "id": "3319360490",
            "restaurant_id": 1124747,
            "menu_category_name": "Starters",
            "menu_category_id": "3319360459",
            "name": "Riptide Fish Tacos",
            "description": "Flour Tortilla / Citrus Battered Fish / Pico De Gallo / Cabbage / Chili Aioli ( 3 per order)",
            "price": {
              "amount": 999,
              "currency": "USD"
            },
            "delivery_price": {
              "amount": 999,
              "currency": "USD"
            },
            "pickup_price": {
              "amount": 999,
              "currency": "USD"
            },
            "tax": 8.7,
            "tax_rate": {
              "name": "AUTOTAX",
              "rate": 8.7,
              "included_in_item_price": false
            },
            "miscellaneous_taxes": [],
            "minimum_cart_total": {
              "amount": 0,
              "currency": "USD"
            },
            "combinable_with_coupons": true,
            "sequence": 1,
            "minimum_price_variation": {
              "amount": 999,
              "currency": "USD"
            },
            "delivery_minimum_price_variation": {
              "amount": 999,
              "currency": "USD"
            },
            "pickup_minimum_price_variation": {
              "amount": 999,
              "currency": "USD"
            },
            "maximum_price_variation": {
              "amount": 999,
              "currency": "USD"
            },
            "delivery_maximum_price_variation": {
              "amount": 999,
              "currency": "USD"
            },
            "pickup_maximum_price_variation": {
              "amount": 999,
              "currency": "USD"
            },
            "available": true,
            "tag_list": [],
            "allowable_order_types": [
              "standard"
            ],
            "menu_item_features": [],
            "in_store_only": false,
            "gh_pos_only": false,
            "routing_tags": [],
            "item_coupon": false,
            "popular": false,
            "deleted": false
          },
          {
            "id": "3319360507",
            "restaurant_id": 1124747,
            "menu_category_name": "Starters",
            "menu_category_id": "3319360459",
            "name": "Fried Calamari",
            "description": "Served with house-made marinara",
            "price": {
              "amount": 899,
              "currency": "USD"
            },
            "delivery_price": {
              "amount": 899,
              "currency": "USD"
            },
            "pickup_price": {
              "amount": 899,
              "currency": "USD"
            },
            "tax": 8.7,
            "tax_rate": {
              "name": "AUTOTAX",
              "rate": 8.7,
              "included_in_item_price": false
            },
            "miscellaneous_taxes": [],
            "minimum_cart_total": {
              "amount": 0,
              "currency": "USD"
            },
            "combinable_with_coupons": true,
            "sequence": 2,
            "minimum_price_variation": {
              "amount": 899,
              "currency": "USD"
            },
            "delivery_minimum_price_variation": {
              "amount": 899,
              "currency": "USD"
            },
            "pickup_minimum_price_variation": {
              "amount": 899,
              "currency": "USD"
            },
            "maximum_price_variation": {
              "amount": 899,
              "currency": "USD"
            },
            "delivery_maximum_price_variation": {
              "amount": 899,
              "currency": "USD"
            },
            "pickup_maximum_price_variation": {
              "amount": 899,
              "currency": "USD"
            },
            "available": true,
            "tag_list": [],
            "allowable_order_types": [
              "standard"
            ],
            "menu_item_features": [],
            "in_store_only": false,
            "gh_pos_only": false,
            "routing_tags": [],
            "item_coupon": false,
            "popular": false,
            "deleted": false
          },
          {
            "id": "3319360505",
            "restaurant_id": 1124747,
            "menu_category_name": "Starters",
            "menu_category_id": "3319360459",
            "name": "Wings",
            "description": "8 wings tossed with your choice of BBQ, medium, hot or lemon pepper served with a side of ranch or bleu cheese.",
            "price": {
              "amount": 1249,
              "currency": "USD"
            },
            "delivery_price": {
              "amount": 1249,
              "currency": "USD"
            },
            "pickup_price": {
              "amount": 1249,
              "currency": "USD"
            },
            "tax": 8.7,
            "tax_rate": {
              "name": "AUTOTAX",
              "rate": 8.7,
              "included_in_item_price": false
            },
            "miscellaneous_taxes": [],
            "minimum_cart_total": {
              "amount": 0,
              "currency": "USD"
            },
            "combinable_with_coupons": true,
            "sequence": 3,
            "minimum_price_variation": {
              "amount": 1249,
              "currency": "USD"
            },
            "delivery_minimum_price_variation": {
              "amount": 1249,
              "currency": "USD"
            },
            "pickup_minimum_price_variation": {
              "amount": 1249,
              "currency": "USD"
            },
            "maximum_price_variation": {
              "amount": 1249,
              "currency": "USD"
            },
            "delivery_maximum_price_variation": {
              "amount": 1249,
              "currency": "USD"
            },
            "pickup_maximum_price_variation": {
              "amount": 1249,
              "currency": "USD"
            },
            "available": true,
            "tag_list": [],
            "allowable_order_types": [
              "standard"
            ],
            "menu_item_features": [],
            "in_store_only": false,
            "gh_pos_only": false,
            "routing_tags": [],
            "item_coupon": false,
            "popular": true,
            "deleted": false
          },
          {
            "id": "3319360476",
            "restaurant_id": 1124747,
            "menu_category_name": "Starters",
            "menu_category_id": "3319360459",
            "name": "Waffle Fries",
            "description": "Potato waffle fries served with ketchup.",
            "price": {
              "amount": 549,
              "currency": "USD"
            },
            "delivery_price": {
              "amount": 549,
              "currency": "USD"
            },
            "pickup_price": {
              "amount": 549,
              "currency": "USD"
            },
            "tax": 8.7,
            "tax_rate": {
              "name": "AUTOTAX",
              "rate": 8.7,
              "included_in_item_price": false
            },
            "miscellaneous_taxes": [],
            "minimum_cart_total": {
              "amount": 0,
              "currency": "USD"
            },
            "combinable_with_coupons": true,
            "sequence": 4,
            "minimum_price_variation": {
              "amount": 549,
              "currency": "USD"
            },
            "delivery_minimum_price_variation": {
              "amount": 549,
              "currency": "USD"
            },
            "pickup_minimum_price_variation": {
              "amount": 549,
              "currency": "USD"
            },
            "maximum_price_variation": {
              "amount": 549,
              "currency": "USD"
            },
            "delivery_maximum_price_variation": {
              "amount": 549,
              "currency": "USD"
            },
            "pickup_maximum_price_variation": {
              "amount": 549,
              "currency": "USD"
            },
            "available": true,
            "tag_list": [],
            "allowable_order_types": [
              "standard"
            ],
            "menu_item_features": [],
            "in_store_only": false,
            "gh_pos_only": false,
            "routing_tags": [],
            "item_coupon": false,
            "popular": false,
            "deleted": false
          },
          {
            "id": "3319360473",
            "restaurant_id": 1124747,
            "menu_category_name": "Starters",
            "menu_category_id": "3319360459",
            "name": "Chicken Tenders",
            "description": "4 tenders served with steak fries and a side of BBQ sauce.",
            "price": {
              "amount": 1049,
              "currency": "USD"
            },
            "delivery_price": {
              "amount": 1049,
              "currency": "USD"
            },
            "pickup_price": {
              "amount": 1049,
              "currency": "USD"
            },
            "tax": 8.7,
            "tax_rate": {
              "name": "AUTOTAX",
              "rate": 8.7,
              "included_in_item_price": false
            },
            "miscellaneous_taxes": [],
            "minimum_cart_total": {
              "amount": 0,
              "currency": "USD"
            },
            "combinable_with_coupons": true,
            "sequence": 5,
            "minimum_price_variation": {
              "amount": 1049,
              "currency": "USD"
            },
            "delivery_minimum_price_variation": {
              "amount": 1049,
              "currency": "USD"
            },
            "pickup_minimum_price_variation": {
              "amount": 1049,
              "currency": "USD"
            },
            "maximum_price_variation": {
              "amount": 1049,
              "currency": "USD"
            },
            "delivery_maximum_price_variation": {
              "amount": 1049,
              "currency": "USD"
            },
            "pickup_maximum_price_variation": {
              "amount": 1049,
              "currency": "USD"
            },
            "available": true,
            "tag_list": [],
            "allowable_order_types": [
              "standard"
            ],
            "menu_item_features": [],
            "in_store_only": false,
            "gh_pos_only": false,
            "routing_tags": [],
            "item_coupon": false,
            "popular": true,
            "deleted": false
          },
          {
            "id": "3319360503",
            "restaurant_id": 1124747,
            "menu_category_name": "Starters",
            "menu_category_id": "3319360459",
            "name": "Popcorn Chicken",
            "description": "Panko tossed chicken bites served with a side of BBQ.",
            "price": {
              "amount": 849,
              "currency": "USD"
            },
            "delivery_price": {
              "amount": 849,
              "currency": "USD"
            },
            "pickup_price": {
              "amount": 849,
              "currency": "USD"
            },
            "tax": 8.7,
            "tax_rate": {
              "name": "AUTOTAX",
              "rate": 8.7,
              "included_in_item_price": false
            },
            "miscellaneous_taxes": [],
            "minimum_cart_total": {
              "amount": 0,
              "currency": "USD"
            },
            "combinable_with_coupons": true,
            "sequence": 6,
            "minimum_price_variation": {
              "amount": 849,
              "currency": "USD"
            },
            "delivery_minimum_price_variation": {
              "amount": 849,
              "currency": "USD"
            },
            "pickup_minimum_price_variation": {
              "amount": 849,
              "currency": "USD"
            },
            "maximum_price_variation": {
              "amount": 849,
              "currency": "USD"
            },
            "delivery_maximum_price_variation": {
              "amount": 849,
              "currency": "USD"
            },
            "pickup_maximum_price_variation": {
              "amount": 849,
              "currency": "USD"
            },
            "available": true,
            "tag_list": [],
            "allowable_order_types": [
              "standard"
            ],
            "menu_item_features": [],
            "in_store_only": false,
            "gh_pos_only": false,
            "routing_tags": [],
            "item_coupon": false,
            "popular": false,
            "deleted": false
          },
          {
            "id": "3319360463",
            "restaurant_id": 1124747,
            "menu_category_name": "Starters",
            "menu_category_id": "3319360459",
            "name": "Sweet Potato Fries",
            "description": "Sweet potato fries served with a side of chili aioli.",
            "price": {
              "amount": 549,
              "currency": "USD"
            },
            "delivery_price": {
              "amount": 549,
              "currency": "USD"
            },
            "pickup_price": {
              "amount": 549,
              "currency": "USD"
            },
            "tax": 8.7,
            "tax_rate": {
              "name": "AUTOTAX",
              "rate": 8.7,
              "included_in_item_price": false
            },
            "miscellaneous_taxes": [],
            "minimum_cart_total": {
              "amount": 0,
              "currency": "USD"
            },
            "combinable_with_coupons": true,
            "sequence": 7,
            "minimum_price_variation": {
              "amount": 549,
              "currency": "USD"
            },
            "delivery_minimum_price_variation": {
              "amount": 549,
              "currency": "USD"
            },
            "pickup_minimum_price_variation": {
              "amount": 549,
              "currency": "USD"
            },
            "maximum_price_variation": {
              "amount": 549,
              "currency": "USD"
            },
            "delivery_maximum_price_variation": {
              "amount": 549,
              "currency": "USD"
            },
            "pickup_maximum_price_variation": {
              "amount": 549,
              "currency": "USD"
            },
            "available": true,
            "tag_list": [],
            "allowable_order_types": [
              "standard"
            ],
            "menu_item_features": [],
            "in_store_only": false,
            "gh_pos_only": false,
            "routing_tags": [],
            "item_coupon": false,
            "popular": false,
            "deleted": false
          },
          {
            "id": "3319360499",
            "restaurant_id": 1124747,
            "menu_category_name": "Starters",
            "menu_category_id": "3319360459",
            "name": "House Fries",
            "description": "Potato steak fries served with ketchup.",
            "price": {
              "amount": 549,
              "currency": "USD"
            },
            "delivery_price": {
              "amount": 549,
              "currency": "USD"
            },
            "pickup_price": {
              "amount": 549,
              "currency": "USD"
            },
            "tax": 8.7,
            "tax_rate": {
              "name": "AUTOTAX",
              "rate": 8.7,
              "included_in_item_price": false
            },
            "miscellaneous_taxes": [],
            "minimum_cart_total": {
              "amount": 0,
              "currency": "USD"
            },
            "combinable_with_coupons": true,
            "sequence": 8,
            "minimum_price_variation": {
              "amount": 549,
              "currency": "USD"
            },
            "delivery_minimum_price_variation": {
              "amount": 549,
              "currency": "USD"
            },
            "pickup_minimum_price_variation": {
              "amount": 549,
              "currency": "USD"
            },
            "maximum_price_variation": {
              "amount": 549,
              "currency": "USD"
            },
            "delivery_maximum_price_variation": {
              "amount": 549,
              "currency": "USD"
            },
            "pickup_maximum_price_variation": {
              "amount": 549,
              "currency": "USD"
            },
            "available": true,
            "tag_list": [],
            "allowable_order_types": [
              "standard"
            ],
            "menu_item_features": [],
            "in_store_only": false,
            "gh_pos_only": false,
            "routing_tags": [],
            "item_coupon": false,
            "popular": false,
            "deleted": false
          }
        ],
        "sequence": 1,
        "available": true
      },
      {
        "id": -975606835,
        "menu_category_id": "3319360461",
        "name": "Salads",
        "menu_item_list": [
          {
            "id": "3319360467",
            "restaurant_id": 1124747,
            "menu_category_name": "Salads",
            "menu_category_id": "3319360461",
            "name": "Ahi Poke Salad",
            "description": "Diced ahi tuna mixed with green onions, sliced cucumbers, edamame, carrot and avocado. Drizzled with poke sauce and served over spring mix.",
            "price": {
              "amount": 1349,
              "currency": "USD"
            },
            "delivery_price": {
              "amount": 1349,
              "currency": "USD"
            },
            "pickup_price": {
              "amount": 1349,
              "currency": "USD"
            },
            "tax": 8.7,
            "tax_rate": {
              "name": "AUTOTAX",
              "rate": 8.7,
              "included_in_item_price": false
            },
            "miscellaneous_taxes": [],
            "minimum_cart_total": {
              "amount": 0,
              "currency": "USD"
            },
            "combinable_with_coupons": true,
            "sequence": 1,
            "minimum_price_variation": {
              "amount": 1349,
              "currency": "USD"
            },
            "delivery_minimum_price_variation": {
              "amount": 1349,
              "currency": "USD"
            },
            "pickup_minimum_price_variation": {
              "amount": 1349,
              "currency": "USD"
            },
            "maximum_price_variation": {
              "amount": 1349,
              "currency": "USD"
            },
            "delivery_maximum_price_variation": {
              "amount": 1349,
              "currency": "USD"
            },
            "pickup_maximum_price_variation": {
              "amount": 1349,
              "currency": "USD"
            },
            "available": true,
            "tag_list": [],
            "allowable_order_types": [
              "standard"
            ],
            "menu_item_features": [],
            "in_store_only": false,
            "gh_pos_only": false,
            "routing_tags": [],
            "item_coupon": false,
            "popular": false,
            "deleted": false
          },
          {
            "id": "3319360475",
            "restaurant_id": 1124747,
            "menu_category_name": "Salads",
            "menu_category_id": "3319360461",
            "name": "House Salad",
            "description": "Served with mixed greens and sesame vinaigrette.",
            "price": {
              "amount": 849,
              "currency": "USD"
            },
            "delivery_price": {
              "amount": 849,
              "currency": "USD"
            },
            "pickup_price": {
              "amount": 849,
              "currency": "USD"
            },
            "tax": 8.7,
            "tax_rate": {
              "name": "AUTOTAX",
              "rate": 8.7,
              "included_in_item_price": false
            },
            "miscellaneous_taxes": [],
            "minimum_cart_total": {
              "amount": 0,
              "currency": "USD"
            },
            "combinable_with_coupons": true,
            "sequence": 2,
            "minimum_price_variation": {
              "amount": 849,
              "currency": "USD"
            },
            "delivery_minimum_price_variation": {
              "amount": 849,
              "currency": "USD"
            },
            "pickup_minimum_price_variation": {
              "amount": 849,
              "currency": "USD"
            },
            "maximum_price_variation": {
              "amount": 849,
              "currency": "USD"
            },
            "delivery_maximum_price_variation": {
              "amount": 849,
              "currency": "USD"
            },
            "pickup_maximum_price_variation": {
              "amount": 849,
              "currency": "USD"
            },
            "available": true,
            "tag_list": [],
            "allowable_order_types": [
              "standard"
            ],
            "menu_item_features": [],
            "in_store_only": false,
            "gh_pos_only": false,
            "routing_tags": [],
            "item_coupon": false,
            "popular": false,
            "deleted": false
          }
        ],
        "sequence": 2,
        "available": true
      },
      {
        "id": -975606836,
        "menu_category_id": "3319360460",
        "name": "Burgers",
        "menu_item_list": [
          {
            "id": "3319360513",
            "restaurant_id": 1124747,
            "menu_category_name": "Burgers",
            "menu_category_id": "3319360460",
            "name": "Bleu Bacon Burger",
            "description": "Bleu cheese crumbles, bacon, tomato, spring mix, avocado and chili aioli served on a locally baked bun ",
            "price": {
              "amount": 1149,
              "currency": "USD"
            },
            "delivery_price": {
              "amount": 1149,
              "currency": "USD"
            },
            "pickup_price": {
              "amount": 1149,
              "currency": "USD"
            },
            "tax": 8.7,
            "tax_rate": {
              "name": "AUTOTAX",
              "rate": 8.7,
              "included_in_item_price": false
            },
            "miscellaneous_taxes": [],
            "minimum_cart_total": {
              "amount": 0,
              "currency": "USD"
            },
            "combinable_with_coupons": true,
            "sequence": 1,
            "minimum_price_variation": {
              "amount": 1249,
              "currency": "USD"
            },
            "delivery_minimum_price_variation": {
              "amount": 1249,
              "currency": "USD"
            },
            "pickup_minimum_price_variation": {
              "amount": 1249,
              "currency": "USD"
            },
            "maximum_price_variation": {
              "amount": 1249,
              "currency": "USD"
            },
            "delivery_maximum_price_variation": {
              "amount": 1249,
              "currency": "USD"
            },
            "pickup_maximum_price_variation": {
              "amount": 1249,
              "currency": "USD"
            },
            "available": true,
            "tag_list": [],
            "allowable_order_types": [
              "standard"
            ],
            "menu_item_features": [],
            "in_store_only": false,
            "gh_pos_only": false,
            "routing_tags": [],
            "item_coupon": false,
            "popular": false,
            "deleted": false
          },
          {
            "id": "3319360520",
            "restaurant_id": 1124747,
            "menu_category_name": "Burgers",
            "menu_category_id": "3319360460",
            "name": "Tucson Burger",
            "description": "Pepper jack, spicy mayo, green chili and avocado served on a locally baked bun ",
            "price": {
              "amount": 1149,
              "currency": "USD"
            },
            "delivery_price": {
              "amount": 1149,
              "currency": "USD"
            },
            "pickup_price": {
              "amount": 1149,
              "currency": "USD"
            },
            "tax": 8.7,
            "tax_rate": {
              "name": "AUTOTAX",
              "rate": 8.7,
              "included_in_item_price": false
            },
            "miscellaneous_taxes": [],
            "minimum_cart_total": {
              "amount": 0,
              "currency": "USD"
            },
            "combinable_with_coupons": true,
            "sequence": 2,
            "minimum_price_variation": {
              "amount": 1249,
              "currency": "USD"
            },
            "delivery_minimum_price_variation": {
              "amount": 1249,
              "currency": "USD"
            },
            "pickup_minimum_price_variation": {
              "amount": 1249,
              "currency": "USD"
            },
            "maximum_price_variation": {
              "amount": 1249,
              "currency": "USD"
            },
            "delivery_maximum_price_variation": {
              "amount": 1249,
              "currency": "USD"
            },
            "pickup_maximum_price_variation": {
              "amount": 1249,
              "currency": "USD"
            },
            "available": true,
            "tag_list": [],
            "allowable_order_types": [
              "standard"
            ],
            "menu_item_features": [],
            "in_store_only": false,
            "gh_pos_only": false,
            "routing_tags": [],
            "item_coupon": false,
            "popular": false,
            "deleted": false
          },
          {
            "id": "3319360483",
            "restaurant_id": 1124747,
            "menu_category_name": "Burgers",
            "menu_category_id": "3319360460",
            "name": "America Burger",
            "description": "American, tomato, lettuce and pickle chili aioli served on a locally baked bun ",
            "price": {
              "amount": 1149,
              "currency": "USD"
            },
            "delivery_price": {
              "amount": 1149,
              "currency": "USD"
            },
            "pickup_price": {
              "amount": 1149,
              "currency": "USD"
            },
            "tax": 8.7,
            "tax_rate": {
              "name": "AUTOTAX",
              "rate": 8.7,
              "included_in_item_price": false
            },
            "miscellaneous_taxes": [],
            "minimum_cart_total": {
              "amount": 0,
              "currency": "USD"
            },
            "combinable_with_coupons": true,
            "sequence": 3,
            "minimum_price_variation": {
              "amount": 1249,
              "currency": "USD"
            },
            "delivery_minimum_price_variation": {
              "amount": 1249,
              "currency": "USD"
            },
            "pickup_minimum_price_variation": {
              "amount": 1249,
              "currency": "USD"
            },
            "maximum_price_variation": {
              "amount": 1249,
              "currency": "USD"
            },
            "delivery_maximum_price_variation": {
              "amount": 1249,
              "currency": "USD"
            },
            "pickup_maximum_price_variation": {
              "amount": 1249,
              "currency": "USD"
            },
            "available": true,
            "tag_list": [],
            "allowable_order_types": [
              "standard"
            ],
            "menu_item_features": [],
            "in_store_only": false,
            "gh_pos_only": false,
            "routing_tags": [],
            "item_coupon": false,
            "popular": false,
            "deleted": false
          },
          {
            "id": "3319360488",
            "restaurant_id": 1124747,
            "menu_category_name": "Burgers",
            "menu_category_id": "3319360460",
            "name": "San Carlos Burger",
            "description": "Pepper jack, guacamole, pico de gallo and jalapeno served on a locally baked bun ",
            "price": {
              "amount": 1149,
              "currency": "USD"
            },
            "delivery_price": {
              "amount": 1149,
              "currency": "USD"
            },
            "pickup_price": {
              "amount": 1149,
              "currency": "USD"
            },
            "tax": 8.7,
            "tax_rate": {
              "name": "AUTOTAX",
              "rate": 8.7,
              "included_in_item_price": false
            },
            "miscellaneous_taxes": [],
            "minimum_cart_total": {
              "amount": 0,
              "currency": "USD"
            },
            "combinable_with_coupons": true,
            "sequence": 4,
            "minimum_price_variation": {
              "amount": 1249,
              "currency": "USD"
            },
            "delivery_minimum_price_variation": {
              "amount": 1249,
              "currency": "USD"
            },
            "pickup_minimum_price_variation": {
              "amount": 1249,
              "currency": "USD"
            },
            "maximum_price_variation": {
              "amount": 1249,
              "currency": "USD"
            },
            "delivery_maximum_price_variation": {
              "amount": 1249,
              "currency": "USD"
            },
            "pickup_maximum_price_variation": {
              "amount": 1249,
              "currency": "USD"
            },
            "available": true,
            "tag_list": [
              {
                "name": "NONFOOD",
                "id": 20000
              }
            ],
            "allowable_order_types": [
              "standard"
            ],
            "menu_item_features": [],
            "in_store_only": false,
            "gh_pos_only": false,
            "routing_tags": [],
            "item_coupon": false,
            "popular": true,
            "deleted": false
          },
          {
            "id": "3319360518",
            "restaurant_id": 1124747,
            "menu_category_name": "Burgers",
            "menu_category_id": "3319360460",
            "name": "BAMF Burger",
            "description": "Our biggest burger. Double meat, double pepper jack, bacon, spicy mayo, spring mix and tomato served on a locally baked bun ",
            "price": {
              "amount": 1449,
              "currency": "USD"
            },
            "delivery_price": {
              "amount": 1449,
              "currency": "USD"
            },
            "pickup_price": {
              "amount": 1449,
              "currency": "USD"
            },
            "tax": 8.7,
            "tax_rate": {
              "name": "AUTOTAX",
              "rate": 8.7,
              "included_in_item_price": false
            },
            "miscellaneous_taxes": [],
            "minimum_cart_total": {
              "amount": 0,
              "currency": "USD"
            },
            "combinable_with_coupons": true,
            "sequence": 5,
            "minimum_price_variation": {
              "amount": 1549,
              "currency": "USD"
            },
            "delivery_minimum_price_variation": {
              "amount": 1549,
              "currency": "USD"
            },
            "pickup_minimum_price_variation": {
              "amount": 1549,
              "currency": "USD"
            },
            "maximum_price_variation": {
              "amount": 1549,
              "currency": "USD"
            },
            "delivery_maximum_price_variation": {
              "amount": 1549,
              "currency": "USD"
            },
            "pickup_maximum_price_variation": {
              "amount": 1549,
              "currency": "USD"
            },
            "available": true,
            "tag_list": [],
            "allowable_order_types": [
              "standard"
            ],
            "menu_item_features": [],
            "in_store_only": false,
            "gh_pos_only": false,
            "routing_tags": [],
            "item_coupon": false,
            "popular": false,
            "deleted": false
          },
          {
            "id": "3319360508",
            "restaurant_id": 1124747,
            "menu_category_name": "Burgers",
            "menu_category_id": "3319360460",
            "name": "Southwest Burger",
            "description": "American, bacon, onion rings, BBQ served on a locally baked bun ",
            "price": {
              "amount": 1149,
              "currency": "USD"
            },
            "delivery_price": {
              "amount": 1149,
              "currency": "USD"
            },
            "pickup_price": {
              "amount": 1149,
              "currency": "USD"
            },
            "tax": 8.7,
            "tax_rate": {
              "name": "AUTOTAX",
              "rate": 8.7,
              "included_in_item_price": false
            },
            "miscellaneous_taxes": [],
            "minimum_cart_total": {
              "amount": 0,
              "currency": "USD"
            },
            "combinable_with_coupons": true,
            "sequence": 6,
            "minimum_price_variation": {
              "amount": 1249,
              "currency": "USD"
            },
            "delivery_minimum_price_variation": {
              "amount": 1249,
              "currency": "USD"
            },
            "pickup_minimum_price_variation": {
              "amount": 1249,
              "currency": "USD"
            },
            "maximum_price_variation": {
              "amount": 1249,
              "currency": "USD"
            },
            "delivery_maximum_price_variation": {
              "amount": 1249,
              "currency": "USD"
            },
            "pickup_maximum_price_variation": {
              "amount": 1249,
              "currency": "USD"
            },
            "available": true,
            "tag_list": [],
            "allowable_order_types": [
              "standard"
            ],
            "menu_item_features": [],
            "in_store_only": false,
            "gh_pos_only": false,
            "routing_tags": [],
            "item_coupon": false,
            "popular": false,
            "deleted": false
          }
        ],
        "sequence": 3,
        "available": true
      },
      {
        "id": -975606834,
        "menu_category_id": "3319360462",
        "name": "Desserts",
        "menu_item_list": [
          {
            "id": "3319360485",
            "restaurant_id": 1124747,
            "menu_category_name": "Desserts",
            "menu_category_id": "3319360462",
            "name": "Cheesecake",
            "description": "",
            "price": {
              "amount": 499,
              "currency": "USD"
            },
            "delivery_price": {
              "amount": 499,
              "currency": "USD"
            },
            "pickup_price": {
              "amount": 499,
              "currency": "USD"
            },
            "tax": 8.7,
            "tax_rate": {
              "name": "AUTOTAX",
              "rate": 8.7,
              "included_in_item_price": false
            },
            "miscellaneous_taxes": [],
            "minimum_cart_total": {
              "amount": 0,
              "currency": "USD"
            },
            "combinable_with_coupons": true,
            "sequence": 1,
            "minimum_price_variation": {
              "amount": 499,
              "currency": "USD"
            },
            "delivery_minimum_price_variation": {
              "amount": 499,
              "currency": "USD"
            },
            "pickup_minimum_price_variation": {
              "amount": 499,
              "currency": "USD"
            },
            "maximum_price_variation": {
              "amount": 499,
              "currency": "USD"
            },
            "delivery_maximum_price_variation": {
              "amount": 499,
              "currency": "USD"
            },
            "pickup_maximum_price_variation": {
              "amount": 499,
              "currency": "USD"
            },
            "available": true,
            "tag_list": [],
            "allowable_order_types": [
              "standard"
            ],
            "menu_item_features": [],
            "in_store_only": false,
            "gh_pos_only": false,
            "routing_tags": [],
            "item_coupon": false,
            "popular": false,
            "deleted": false
          },
          {
            "id": "3319360491",
            "restaurant_id": 1124747,
            "menu_category_name": "Desserts",
            "menu_category_id": "3319360462",
            "name": "Brownie",
            "description": "",
            "price": {
              "amount": 499,
              "currency": "USD"
            },
            "delivery_price": {
              "amount": 499,
              "currency": "USD"
            },
            "pickup_price": {
              "amount": 499,
              "currency": "USD"
            },
            "tax": 8.7,
            "tax_rate": {
              "name": "AUTOTAX",
              "rate": 8.7,
              "included_in_item_price": false
            },
            "miscellaneous_taxes": [],
            "minimum_cart_total": {
              "amount": 0,
              "currency": "USD"
            },
            "combinable_with_coupons": true,
            "sequence": 2,
            "minimum_price_variation": {
              "amount": 499,
              "currency": "USD"
            },
            "delivery_minimum_price_variation": {
              "amount": 499,
              "currency": "USD"
            },
            "pickup_minimum_price_variation": {
              "amount": 499,
              "currency": "USD"
            },
            "maximum_price_variation": {
              "amount": 499,
              "currency": "USD"
            },
            "delivery_maximum_price_variation": {
              "amount": 499,
              "currency": "USD"
            },
            "pickup_maximum_price_variation": {
              "amount": 499,
              "currency": "USD"
            },
            "available": true,
            "tag_list": [],
            "allowable_order_types": [
              "standard"
            ],
            "menu_item_features": [],
            "in_store_only": false,
            "gh_pos_only": false,
            "routing_tags": [],
            "item_coupon": false,
            "popular": false,
            "deleted": false
          }
        ],
        "sequence": 4,
        "available": true
      },
      {
        "id": -975606838,
        "menu_category_id": "3319360458",
        "name": "Drinks",
        "menu_item_list": [
          {
            "id": "3319360519",
            "restaurant_id": 1124747,
            "menu_category_name": "Drinks",
            "menu_category_id": "3319360458",
            "name": "Pure Leaf Tea (unsweetened)",
            "description": "18.5oz",
            "price": {
              "amount": 250,
              "currency": "USD"
            },
            "delivery_price": {
              "amount": 250,
              "currency": "USD"
            },
            "pickup_price": {
              "amount": 250,
              "currency": "USD"
            },
            "tax": 8.7,
            "tax_rate": {
              "name": "AUTOTAX",
              "rate": 8.7,
              "included_in_item_price": false
            },
            "miscellaneous_taxes": [],
            "minimum_cart_total": {
              "amount": 0,
              "currency": "USD"
            },
            "combinable_with_coupons": true,
            "sequence": 1,
            "minimum_price_variation": {
              "amount": 250,
              "currency": "USD"
            },
            "delivery_minimum_price_variation": {
              "amount": 250,
              "currency": "USD"
            },
            "pickup_minimum_price_variation": {
              "amount": 250,
              "currency": "USD"
            },
            "maximum_price_variation": {
              "amount": 250,
              "currency": "USD"
            },
            "delivery_maximum_price_variation": {
              "amount": 250,
              "currency": "USD"
            },
            "pickup_maximum_price_variation": {
              "amount": 250,
              "currency": "USD"
            },
            "available": true,
            "tag_list": [
              {
                "name": "NONFOOD",
                "id": 20000
              }
            ],
            "allowable_order_types": [
              "standard"
            ],
            "menu_item_features": [],
            "in_store_only": false,
            "gh_pos_only": false,
            "routing_tags": [],
            "item_coupon": false,
            "popular": false,
            "deleted": false
          },
          {
            "id": "3319360500",
            "restaurant_id": 1124747,
            "menu_category_name": "Drinks",
            "menu_category_id": "3319360458",
            "name": "Diet Pepsi",
            "description": "12 oz Can",
            "price": {
              "amount": 250,
              "currency": "USD"
            },
            "delivery_price": {
              "amount": 250,
              "currency": "USD"
            },
            "pickup_price": {
              "amount": 250,
              "currency": "USD"
            },
            "tax": 8.7,
            "tax_rate": {
              "name": "AUTOTAX",
              "rate": 8.7,
              "included_in_item_price": false
            },
            "miscellaneous_taxes": [],
            "minimum_cart_total": {
              "amount": 0,
              "currency": "USD"
            },
            "combinable_with_coupons": true,
            "sequence": 2,
            "minimum_price_variation": {
              "amount": 250,
              "currency": "USD"
            },
            "delivery_minimum_price_variation": {
              "amount": 250,
              "currency": "USD"
            },
            "pickup_minimum_price_variation": {
              "amount": 250,
              "currency": "USD"
            },
            "maximum_price_variation": {
              "amount": 250,
              "currency": "USD"
            },
            "delivery_maximum_price_variation": {
              "amount": 250,
              "currency": "USD"
            },
            "pickup_maximum_price_variation": {
              "amount": 250,
              "currency": "USD"
            },
            "available": true,
            "tag_list": [],
            "allowable_order_types": [
              "standard"
            ],
            "menu_item_features": [],
            "in_store_only": false,
            "gh_pos_only": false,
            "routing_tags": [],
            "item_coupon": false,
            "popular": false,
            "deleted": false
          },
          {
            "id": "3319360521",
            "restaurant_id": 1124747,
            "menu_category_name": "Drinks",
            "menu_category_id": "3319360458",
            "name": "Pepsi",
            "description": "12 oz Can",
            "price": {
              "amount": 250,
              "currency": "USD"
            },
            "delivery_price": {
              "amount": 250,
              "currency": "USD"
            },
            "pickup_price": {
              "amount": 250,
              "currency": "USD"
            },
            "tax": 8.7,
            "tax_rate": {
              "name": "AUTOTAX",
              "rate": 8.7,
              "included_in_item_price": false
            },
            "miscellaneous_taxes": [],
            "minimum_cart_total": {
              "amount": 0,
              "currency": "USD"
            },
            "combinable_with_coupons": true,
            "sequence": 3,
            "minimum_price_variation": {
              "amount": 250,
              "currency": "USD"
            },
            "delivery_minimum_price_variation": {
              "amount": 250,
              "currency": "USD"
            },
            "pickup_minimum_price_variation": {
              "amount": 250,
              "currency": "USD"
            },
            "maximum_price_variation": {
              "amount": 250,
              "currency": "USD"
            },
            "delivery_maximum_price_variation": {
              "amount": 250,
              "currency": "USD"
            },
            "pickup_maximum_price_variation": {
              "amount": 250,
              "currency": "USD"
            },
            "available": true,
            "tag_list": [],
            "allowable_order_types": [
              "standard"
            ],
            "menu_item_features": [],
            "in_store_only": false,
            "gh_pos_only": false,
            "routing_tags": [],
            "item_coupon": false,
            "popular": false,
            "deleted": false
          },
          {
            "id": "3319360517",
            "restaurant_id": 1124747,
            "menu_category_name": "Drinks",
            "menu_category_id": "3319360458",
            "name": "Bottled Water",
            "description": "16oz Bottle",
            "price": {
              "amount": 249,
              "currency": "USD"
            },
            "delivery_price": {
              "amount": 249,
              "currency": "USD"
            },
            "pickup_price": {
              "amount": 249,
              "currency": "USD"
            },
            "tax": 8.7,
            "tax_rate": {
              "name": "AUTOTAX",
              "rate": 8.7,
              "included_in_item_price": false
            },
            "miscellaneous_taxes": [],
            "minimum_cart_total": {
              "amount": 0,
              "currency": "USD"
            },
            "combinable_with_coupons": true,
            "sequence": 4,
            "minimum_price_variation": {
              "amount": 249,
              "currency": "USD"
            },
            "delivery_minimum_price_variation": {
              "amount": 249,
              "currency": "USD"
            },
            "pickup_minimum_price_variation": {
              "amount": 249,
              "currency": "USD"
            },
            "maximum_price_variation": {
              "amount": 249,
              "currency": "USD"
            },
            "delivery_maximum_price_variation": {
              "amount": 249,
              "currency": "USD"
            },
            "pickup_maximum_price_variation": {
              "amount": 249,
              "currency": "USD"
            },
            "available": true,
            "tag_list": [
              {
                "name": "NONFOOD",
                "id": 20000
              }
            ],
            "allowable_order_types": [
              "standard"
            ],
            "menu_item_features": [],
            "in_store_only": false,
            "gh_pos_only": false,
            "routing_tags": [],
            "item_coupon": false,
            "popular": false,
            "deleted": false
          },
          {
            "id": "3319360487",
            "restaurant_id": 1124747,
            "menu_category_name": "Drinks",
            "menu_category_id": "3319360458",
            "name": "Mtn Dew ",
            "description": "12 oz Can",
            "price": {
              "amount": 250,
              "currency": "USD"
            },
            "delivery_price": {
              "amount": 250,
              "currency": "USD"
            },
            "pickup_price": {
              "amount": 250,
              "currency": "USD"
            },
            "tax": 8.7,
            "tax_rate": {
              "name": "AUTOTAX",
              "rate": 8.7,
              "included_in_item_price": false
            },
            "miscellaneous_taxes": [],
            "minimum_cart_total": {
              "amount": 0,
              "currency": "USD"
            },
            "combinable_with_coupons": true,
            "sequence": 5,
            "minimum_price_variation": {
              "amount": 250,
              "currency": "USD"
            },
            "delivery_minimum_price_variation": {
              "amount": 250,
              "currency": "USD"
            },
            "pickup_minimum_price_variation": {
              "amount": 250,
              "currency": "USD"
            },
            "maximum_price_variation": {
              "amount": 250,
              "currency": "USD"
            },
            "delivery_maximum_price_variation": {
              "amount": 250,
              "currency": "USD"
            },
            "pickup_maximum_price_variation": {
              "amount": 250,
              "currency": "USD"
            },
            "available": true,
            "tag_list": [],
            "allowable_order_types": [
              "standard"
            ],
            "menu_item_features": [],
            "in_store_only": false,
            "gh_pos_only": false,
            "routing_tags": [],
            "item_coupon": false,
            "popular": false,
            "deleted": false
          },
          {
            "id": "3319360504",
            "restaurant_id": 1124747,
            "menu_category_name": "Drinks",
            "menu_category_id": "3319360458",
            "name": "Sprite",
            "description": "12 oz Can",
            "price": {
              "amount": 250,
              "currency": "USD"
            },
            "delivery_price": {
              "amount": 250,
              "currency": "USD"
            },
            "pickup_price": {
              "amount": 250,
              "currency": "USD"
            },
            "tax": 8.7,
            "tax_rate": {
              "name": "AUTOTAX",
              "rate": 8.7,
              "included_in_item_price": false
            },
            "miscellaneous_taxes": [],
            "minimum_cart_total": {
              "amount": 0,
              "currency": "USD"
            },
            "combinable_with_coupons": true,
            "sequence": 6,
            "minimum_price_variation": {
              "amount": 250,
              "currency": "USD"
            },
            "delivery_minimum_price_variation": {
              "amount": 250,
              "currency": "USD"
            },
            "pickup_minimum_price_variation": {
              "amount": 250,
              "currency": "USD"
            },
            "maximum_price_variation": {
              "amount": 250,
              "currency": "USD"
            },
            "delivery_maximum_price_variation": {
              "amount": 250,
              "currency": "USD"
            },
            "pickup_maximum_price_variation": {
              "amount": 250,
              "currency": "USD"
            },
            "available": true,
            "tag_list": [
              {
                "name": "NONFOOD",
                "id": 20000
              }
            ],
            "allowable_order_types": [
              "standard"
            ],
            "menu_item_features": [],
            "in_store_only": false,
            "gh_pos_only": false,
            "routing_tags": [],
            "item_coupon": false,
            "popular": false,
            "deleted": false
          }
        ],
        "sequence": 5,
        "available": true
      }
    ],
    "restaurant_coupons": [],
    "just_in_time_orders": false,
    "restaurant_cdn_image_url": "http://s1.seamless.com/-/ri/gh/1124747",
    "media_image": {
      "base_url": "https://media-cdn.grubhub.com/image/upload/",
      "public_id": "pzkxn5p5uqllcgtydipf",
      "format": "jpg",
      "tag": "logo"
    },
    "rating": {
      "rating_count": "221",
      "rating_value": "3"
    },
    "price_rating": "1",
    "rating_bayesian_half_point": {
      "rating_count": "221",
      "rating_value": "3.5"
    },
    "rating_bayesian10_point": {
      "rating_count": "221",
      "rating_value": "3.4"
    },
    "alcohol_enabled": false,
    "alcohol_market_status": "DISABLED",
    "faceted_rating_data": {
      "review_data": {
        "total_count": 71,
        "valid_count": 67,
        "top_review": {
          "rating_value": 4,
          "review_text": "Restaurant has great food",
          "reviewer_display_name": "Tasha",
          "time_created": null
        }
      },
      "faceted_rating_list": [
        {
          "facet_name": "Delivery Speed",
          "facet_type": "delivery_speed",
          "response_count": 205,
          "positive_response_count": 165,
          "positive_response_percentage": 0.8048780487804879
        },
        {
          "facet_name": "Order Accuracy",
          "facet_type": "order_accuracy",
          "response_count": 224,
          "positive_response_count": 177,
          "positive_response_percentage": 0.7901785714285714
        },
        {
          "facet_name": "Food Quality",
          "facet_type": "food_quality",
          "response_count": 216,
          "positive_response_count": 143,
          "positive_response_percentage": 0.6620370370370371
        }
      ],
      "faceted_rating_too_few": false
    },
    "additional_media_images": {
      "LOGO_HOME_PAGE": {
        "base_url": "https://media-cdn.grubhub.com/image/upload/",
        "public_id": "pzkxn5p5uqllcgtydipf",
        "format": "jpg",
        "tag": "logo"
      },
      "MENU_PAGE": {
        "base_url": "https://media-cdn.grubhub.com/image/upload/",
        "public_id": "pzkxn5p5uqllcgtydipf",
        "format": "jpg",
        "tag": "logo"
      },
      "SEARCH_HOME_PAGE": {
        "base_url": "https://media-cdn.grubhub.com/image/upload/",
        "public_id": "ylajyuokajqxh4tvicht",
        "format": "jpg",
        "tag": "search"
      },
      "SEARCH_RESULTS_PAGE": {
        "base_url": "https://media-cdn.grubhub.com/image/upload/",
        "public_id": "ylajyuokajqxh4tvicht",
        "format": "jpg",
        "tag": "search"
      },
      "HEADER_BACKGROUND": {
        "base_url": "https://media-cdn.grubhub.com/image/upload/",
        "public_id": "owt6zxyscdokqzizguvx",
        "format": "jpg",
        "tag": "header_background"
      }
    },
    "tag_list": [],
    "available_promo_codes": [],
    "available_offers": [],
    "available_progress_campaigns": [],
    "merchant_url_path": "southwest-grillers-940-e-university-blvd-tucson",
    "order_type_settings": {
      "service_fee": {
        "name": "Service fee",
        "description": "A service fee of 1.0% for delivery orders will be charged with Southwest Grillers.",
        "delivery_fee": {
          "fee_type": "PERCENT",
          "percent_value": 1
        },
        "delivery_service_fee_allocation_info": {
          "attribution": "GRUBHUB"
        },
        "fee_allocation_info": {
          "fee_allocation_type": "GRUBHUB"
        }
      },
      "small_order_fee": {
        "name": "Small order delivery fee",
        "description": "A small order delivery fee applies to your Southwest Grillers subtotal of $9.89 or less.",
        "minimum_order_value_cents": 1000,
        "fee": {
          "fee_type": "FLAT",
          "flat_cents_value": {
            "amount": 200,
            "currency": "USD"
          }
        },
        "fee_allocation_info": {
          "attribution": "GRUBHUB"
        }
      },
      "merchant_status": {
        "category": "ACTIVE",
        "category_description": "Active",
        "description": "Premium",
        "requires_attrition_reason": false,
        "status": "PREMIUM"
      },
      "delivery_estimate_minutes": 60,
      "pickup_estimate_minutes": 20
    },
    "pickup_tips_disabled": false,
    "special_instructions_disabled": false,
    "restaurant_tags": [
      "PRICING_ELIGIBLE_FOR_STANDARD_ORDER",
      "SUBSCRIPTION_ELIGIBLE_FOR_STANDARD_ORDER"
    ],
    "version_ids": {
      "catalog": "v1:f3uYoqFNO_M7uTUDhIorsQV2L4Woi7pX"
    },
    "shared_cart": true,
    "excluded_menu_item_count": 0,
    "aggregations": {
      "menu_item_tags": {
        "values": {
          "NONFOOD": 4
        }
      }
    },
    "menu_item_features": [],
    "pos_integrated": false,
    "data_bytes": 126876,
    "menu_data_bytes": 52042,
    "service_fee_taxable": true,
    "service_fee_taxable_when_delivery_only": false,
    "delivery_fee_taxable_when_delivery_only": false,
    "cash_tip_allowed": false,
    "is_too_few": false,
    "too_few": false
  }
}